voicecut/__init__.py
voicecut/cli.py
voicecut/py.typed
voicecut/splitter.py
voicecut-0.1.0.dist-info/licenses/LICENSE
voicecut-0.1.0.dist-info/WHEEL
voicecut-0.1.0.dist-info/entry_points.txt
voicecut-0.1.0.dist-info/METADATA
voicecut-0.1.0.dist-info/RECORD
