Metadata-Version: 2.4
Name: voicecut
Version: 0.1.0
Summary: A cli tool for cutting a long audio into segments by silence.
Keywords: utility,audio
Author: Mikhail Pankin
Author-email: Mikhail Pankin <mishapankin@gmail.com>
License-Expression: MIT
License-File: LICENSE
Classifier: Development Status :: 4 - Beta
Classifier: Intended Audience :: Developers
Classifier: License :: OSI Approved :: MIT License
Classifier: Programming Language :: Python :: 3
Classifier: Programming Language :: Python :: 3.9
Classifier: Programming Language :: Python :: 3.10
Classifier: Programming Language :: Python :: 3.11
Classifier: Programming Language :: Python :: 3.12
Classifier: Programming Language :: Python :: 3.13
Classifier: Programming Language :: Python :: 3.14
Classifier: Programming Language :: Python :: 3.15
Classifier: Topic :: Multimedia :: Sound/Audio :: Analysis
Classifier: Topic :: Software Development :: Libraries :: Python Modules
Requires-Dist: pydub>=0.25.1
Requires-Python: >=3.9
Project-URL: Documentation, https://github.com/mishapankin/voicecut#readme
Project-URL: Homepage, https://github.com/mishapankin/voicecut
Project-URL: Issues, https://github.com/mishapankin/voicecut/issues
Project-URL: Repository, https://github.com/mishapankin/voicecut
